rasa_audiocodes/__init__.py
rasa_audiocodes/audiocodes.py
rasa_audiocodes/version.py
rasa_audiocodes-1.0.0.dist-info/LICENSE.txt
rasa_audiocodes-1.0.0.dist-info/METADATA
rasa_audiocodes-1.0.0.dist-info/WHEEL
rasa_audiocodes-1.0.0.dist-info/top_level.txt
rasa_audiocodes-1.0.0.dist-info/RECORD
