Metadata-Version: 2.1
Name: rasa-audiocodes
Version: 1.0.0
Summary: Integrate Rasa with AudioCodes VoiceAI Connect
Author-email: "AudioCodes Ltd." <yaakov.bivas@audiocodes.com>
Project-URL: Homepage, https://github.com/ac-voice-ai/rasa-audiocodes
Project-URL: Bug Reports, https://github.com/ac-voice-ai/rasa-audiocodes/issues
Project-URL: Source, https://github.com/ac-voice-ai/rasa-audiocodes
Classifier: Programming Language :: Python
Classifier: Programming Language :: Python :: 3.6
Classifier: Programming Language :: Python :: 3.7
Classifier: Programming Language :: Python :: 3.8
Classifier: Programming Language :: Python :: 3.9
Classifier: Programming Language :: Python :: 3.10
Classifier: License :: OSI Approved :: Apache Software License
License-File: LICENSE.txt
Requires-Dist: rasa-sdk (>=1.3.2)
